{"b": ["\u044c"], "g": ["9"], "i": ["1"], "n": ["u"], "o": ["0"], "p": ["q"], "q": ["p"], "s": ["$"], "u": ["*u", "n", "\u00b5"], "v": ["\u2200"], "w": ["\u0448"], "x": ["\u00d7"], "A": ["\u2200"], "E": ["\u2203"], "G": ["6"], "I": ["1"], "L": ["|_"], "M": ["|\\/|"], "N": ["|\\|"], "O": ["0"], "S": ["$"], "W": ["\u0428"], "Z": ["\u01b5"], "\u0431": ["b"], "\u0433": ["|\u203e"], "\u0435": ["\u03b5"], "\u0436": [">|<"], "\u0437": ["3"], "\u0438": ["u"], "\u043a": ["k"], "\u043b": ["jl"], "\u043e": ["0"], "\u043f": ["n"], "\u0442": ["t"], "\u0444": ["\u00b0l\u00b0"], "\u0445": ["\u00d7"], "\u0447": ["4"], "\u0448": ["w"], "\u044a": ["\u203eb"], "\u044b": ["bl"], "\u044c": ["b"], "\u044d": ["\u0454"], "\u044f": ["9"], "\u0410": ["\u2200"], "\u0413": ["|\u203e"], "e": ["\u03b5"], "\u0415": ["\u2203"], "\u0416": [">|<"], "\u0418": ["N"], "\u041a": ["k"], "\u041b": ["JI"], "\u041c": ["|\\/|"], "\u041d": ["|-|"], "\u041e": ["0"], "\u041f": ["|\u203e|"], "\u0424": ["0|0"], "\u0427": ["4"], "\u0428": ["W"], "\u042a": ["\u203e\u042c"], "\u042b": ["\u042cl"], "\u042c": ["b"], "\u0491": ["\u0433'"], "\u0456": ["l"], "\u0490": ["\u0413\u2019"], "\u0407": ["\u2019l\u2019"], "U": ["*U"], "\u043c": ["\u00b5"]}